odoo/addons/account_analytic_no_lines/README.rst
odoo/addons/account_analytic_no_lines/__init__.py
odoo/addons/account_analytic_no_lines/__manifest__.py
odoo/addons/account_analytic_no_lines/i18n/account_analytic_no_lines.pot
odoo/addons/account_analytic_no_lines/i18n/ca.po
odoo/addons/account_analytic_no_lines/i18n/cs_CZ.po
odoo/addons/account_analytic_no_lines/i18n/de.po
odoo/addons/account_analytic_no_lines/i18n/el_GR.po
odoo/addons/account_analytic_no_lines/i18n/es.po
odoo/addons/account_analytic_no_lines/i18n/es_EC.po
odoo/addons/account_analytic_no_lines/i18n/es_MX.po
odoo/addons/account_analytic_no_lines/i18n/fi.po
odoo/addons/account_analytic_no_lines/i18n/fr.po
odoo/addons/account_analytic_no_lines/i18n/gu_IN.po
odoo/addons/account_analytic_no_lines/i18n/hi_IN.po
odoo/addons/account_analytic_no_lines/i18n/hr.po
odoo/addons/account_analytic_no_lines/i18n/hr_HR.po
odoo/addons/account_analytic_no_lines/i18n/it.po
odoo/addons/account_analytic_no_lines/i18n/nl.po
odoo/addons/account_analytic_no_lines/i18n/nl_NL.po
odoo/addons/account_analytic_no_lines/i18n/pt.po
odoo/addons/account_analytic_no_lines/i18n/pt_BR.po
odoo/addons/account_analytic_no_lines/i18n/ru.po
odoo/addons/account_analytic_no_lines/i18n/sk_SK.po
odoo/addons/account_analytic_no_lines/i18n/sl.po
odoo/addons/account_analytic_no_lines/i18n/zh_CN.po
odoo/addons/account_analytic_no_lines/migrations/14.0.1.0.0/pre-migration.py
odoo/addons/account_analytic_no_lines/models/__init__.py
odoo/addons/account_analytic_no_lines/models/account_analytic_account.py
odoo/addons/account_analytic_no_lines/models/account_move_line.py
odoo/addons/account_analytic_no_lines/readme/CONTRIBUTORS.rst
odoo/addons/account_analytic_no_lines/readme/DESCRIPTION.rst
odoo/addons/account_analytic_no_lines/security/data_account_analytic_group.xml
odoo/addons/account_analytic_no_lines/static/description/icon.png
odoo/addons/account_analytic_no_lines/static/description/index.html
odoo14_addon_account_analytic_no_lines-14.0.1.0.1.dev13.dist-info/METADATA
odoo14_addon_account_analytic_no_lines-14.0.1.0.1.dev13.dist-info/WHEEL
odoo14_addon_account_analytic_no_lines-14.0.1.0.1.dev13.dist-info/top_level.txt
odoo14_addon_account_analytic_no_lines-14.0.1.0.1.dev13.dist-info/RECORD
